setup.cfg
setup.py
bigchaindb_shared/__init__.py
bigchaindb_shared/__main__.py
bigchaindb_shared/api.py
bigchaindb_shared/errors.py
bigchaindb_shared.egg-info/PKG-INFO
bigchaindb_shared.egg-info/SOURCES.txt
bigchaindb_shared.egg-info/dependency_links.txt
bigchaindb_shared.egg-info/top_level.txt
bigchaindb_shared/lib/x86_64/libHSbigchaindb-0.2.0-Cuz37eK1neP9YpTjNeTjTy-ghc8.0.1.so
bigchaindb_shared/lib/x86_64/libbigchaindb_shared.so
bigchaindb_shared/lib/x86_64/libs/libHSaeson-0.11.2.1-EvvVy7RUk571N9rAPFuWeR-ghc8.0.1.so
bigchaindb_shared/lib/x86_64/libs/libHSaeson-pretty-0.8.2-7y8tUySNKSMK2CTKbVRWr3-ghc8.0.1.so
bigchaindb_shared/lib/x86_64/libs/libHSaeson-quick-0.1.1.2-FerRu49elFEBGdZEby2B9w-ghc8.0.1.so
bigchaindb_shared/lib/x86_64/libs/libHSarray-0.5.1.1-ghc8.0.1.so
bigchaindb_shared/lib/x86_64/libs/libHSasn1-encoding-0.9.4-2Zu5ldLYD571Aw26w0CWF6-ghc8.0.1.so
bigchaindb_shared/lib/x86_64/libs/libHSasn1-parse-0.9.4-Ai83ACtrOir9VlSOQtWm2F-ghc8.0.1.so
bigchaindb_shared/lib/x86_64/libs/libHSasn1-types-0.3.2-4Rz223aP8OG6vnHYiLX5Ab-ghc8.0.1.so
bigchaindb_shared/lib/x86_64/libs/libHSasync-2.1.1-xFiBzw9xoB8HPZAuxUY2o-ghc8.0.1.so
bigchaindb_shared/lib/x86_64/libs/libHSattoparsec-0.13.1.0-5Olk1S76r1CDYzFS6V3sZR-ghc8.0.1.so
bigchaindb_shared/lib/x86_64/libs/libHSbase-4.9.0.0-ghc8.0.1.so
bigchaindb_shared/lib/x86_64/libs/libHSbase-compat-0.9.1-tmPpmtbHbvIDjFWbkjGrR-ghc8.0.1.so
bigchaindb_shared/lib/x86_64/libs/libHSbase58-bytestring-0.1.0-G6TScsXhE0u66Y2cCLF7Mo-ghc8.0.1.so
bigchaindb_shared/lib/x86_64/libs/libHSbase64-bytestring-1.0.0.1-In9M41tLtcS9QYt3QpGpNY-ghc8.0.1.so
bigchaindb_shared/lib/x86_64/libs/libHSbinary-0.8.3.0-ghc8.0.1.so
bigchaindb_shared/lib/x86_64/libs/libHSblaze-builder-0.4.0.2-KWDLbdBYSBoALiMW0LHIz1-ghc8.0.1.so
bigchaindb_shared/lib/x86_64/libs/libHSbyteable-0.1.1-15aIBCArSOBEnGxArzrDTM-ghc8.0.1.so
bigchaindb_shared/lib/x86_64/libs/libHSbytestring-0.10.8.1-ghc8.0.1.so
bigchaindb_shared/lib/x86_64/libs/libHScase-insensitive-1.2.0.7-FlqweN7AuKj9EdU2arVEt4-ghc8.0.1.so
bigchaindb_shared/lib/x86_64/libs/libHScereal-0.5.4.0-2FJYHGgtE5C3SxaZjt25xS-ghc8.0.1.so
